memx/__init__.py
memx/factory/__init__.py
memx/memory/__init__.py
memx/memory/mongodb.py
memx/memory/postgres.py
memx/memory/redis.py
memx/memory/simple.py
memx/memory/sqlite.py
memx_lm-0.1.7.data/data/README.md
memx_lm-0.1.7.dist-info/METADATA
memx_lm-0.1.7.dist-info/WHEEL
memx_lm-0.1.7.dist-info/licenses/LICENSE
memx_lm-0.1.7.dist-info/RECORD
