Metadata-Version: 2.4
Name: memx-lm
Version: 0.1.7
Summary: Lightweight and extensible memory layer for LLMs
Author-email: Pablo Galilea <pgalilea@me.com>
License-Expression: MIT
License-File: LICENSE
Requires-Python: >=3.11
Requires-Dist: aiofiles>=25.1.0
Requires-Dist: orjson>=3.11.4
Provides-Extra: all
Requires-Dist: aiosqlite>=0.21.0; extra == 'all'
Requires-Dist: psycopg>=3.2.12; extra == 'all'
Requires-Dist: pymongo>=4.15.3; extra == 'all'
Requires-Dist: sqlalchemy[asyncio,postgresql-psycopg]>=2.0.44; extra == 'all'
Provides-Extra: mongodb
Requires-Dist: pymongo>=4.15.3; extra == 'mongodb'
Provides-Extra: postgres
Requires-Dist: psycopg>=3.2.12; extra == 'postgres'
Requires-Dist: sqlalchemy[asyncio,postgresql-psycopg]>=2.0.44; extra == 'postgres'
Provides-Extra: sqlite
Requires-Dist: aiosqlite>=0.21.0; extra == 'sqlite'
Requires-Dist: sqlalchemy[asyncio]>=2.0.44; extra == 'sqlite'
